kura/__init__.py
kura/cache.py
kura/checkpoint.py
kura/clio_reference.md
kura/cluster.py
kura/dimensionality.py
kura/embedding.py
kura/hdbscan.py
kura/k_means.py
kura/meta_cluster.py
kura/summarisation.py
kura/utils.py
kura/visualization.py
kura/base_classes/__init__.py
kura/base_classes/cache.py
kura/base_classes/checkpoint.py
kura/base_classes/cluster.py
kura/base_classes/clustering_method.py
kura/base_classes/dimensionality.py
kura/base_classes/embedding.py
kura/base_classes/meta_cluster.py
kura/base_classes/summarisation.py
kura/checkpoints/README.md
kura/checkpoints/__init__.py
kura/checkpoints/hf_dataset.py
kura/checkpoints/jsonl.py
kura/checkpoints/multi.py
kura/checkpoints/parquet.py
kura/cli/cli.py
kura/cli/server.py
kura/types/__init__.py
kura/types/cluster.py
kura/types/conversation.py
kura/types/dimensionality.py
kura/types/summarisation.py
kura/static/dist/index.html
kura/static/dist/vite.svg
kura/static/dist/assets/index-BKEf1cwf.css
kura/static/dist/assets/index-CP98eMHA.js
kura-0.5.4.dist-info/METADATA
kura-0.5.4.dist-info/WHEEL
kura-0.5.4.dist-info/entry_points.txt
kura-0.5.4.dist-info/RECORD
