Metadata-Version: 2.4
Name: kura
Version: 0.5.4
Summary: Kura is a tool for analysing and visualising chat data
Author-email: Ivan Leo <ivanleomk@gmail.com>
Requires-Python: >=3.10
Requires-Dist: datasets>=3.6.0
Requires-Dist: diskcache>=5.6.3
Requires-Dist: eval-type-backport>=0.2.2
Requires-Dist: fastapi[standard]>=0.115.6
Requires-Dist: hdbscan>=0.8.40
Requires-Dist: instructor>=1.8.3
Requires-Dist: jsonref>=1.1.0
Requires-Dist: pandas>=2.2.3
Requires-Dist: scikit-learn>=1.6.0
Requires-Dist: sqlmodel>=0.0.14
Requires-Dist: thefuzz>=0.22.1
Requires-Dist: typer>=0.9.0
Requires-Dist: umap-learn>=0.5.7
Requires-Dist: uvicorn>=0.34.0
